copier_template_extensions-0.3.3.dist-info/METADATA
copier_template_extensions-0.3.3.dist-info/WHEEL
copier_template_extensions-0.3.3.dist-info/entry_points.txt
copier_template_extensions-0.3.3.dist-info/licenses/LICENSE
copier_template_extensions/__init__.py
copier_template_extensions/_internal/__init__.py
copier_template_extensions/_internal/context.py
copier_template_extensions/_internal/debug.py
copier_template_extensions/_internal/loader.py
copier_template_extensions/py.typed
copier_templates_extensions/__init__.py
copier_template_extensions-0.3.3.dist-info/RECORD
